aic/__init__.py
aic/__main__.py
aic/commit_lint.py
aic/config.py
aic/git.py
aic/log.py
aic/pretty.py
aic/token.py
aic/api/__init__.py
aic/api/openrouter.py
aic/cli/__init__.py
aic/cli/list_models.py
aic/cli/main.py
aic/prompt/__init__.py
aic/prompt/_type.py
aic/prompt/template.py
ai_commit_cli-0.8.3.dist-info/METADATA
ai_commit_cli-0.8.3.dist-info/WHEEL
ai_commit_cli-0.8.3.dist-info/entry_points.txt
ai_commit_cli-0.8.3.dist-info/RECORD
