Metadata-Version: 2.3
Name: ai-commit-cli
Version: 0.8.3
Summary: Add your description here
Author-email: liblaf <30631553+liblaf@users.noreply.github.com>
License: MIT
Requires-Python: >=3.11
Requires-Dist: babel>=2.14.0
Requires-Dist: httpx[socks]>=0.27.0
Requires-Dist: loguru>=0.7.2
Requires-Dist: openai>=1.23.6
Requires-Dist: pydantic>=2.7.1
Requires-Dist: questionary>=2.0.1
Requires-Dist: rich>=13.7.1
Requires-Dist: tiktoken>=0.6.0
Requires-Dist: typer>=0.12.3
